elasticsearch8_dsl/__init__.py
elasticsearch8_dsl/aggs.py
elasticsearch8_dsl/analysis.py
elasticsearch8_dsl/connections.py
elasticsearch8_dsl/document.py
elasticsearch8_dsl/exceptions.py
elasticsearch8_dsl/faceted_search.py
elasticsearch8_dsl/field.py
elasticsearch8_dsl/function.py
elasticsearch8_dsl/index.py
elasticsearch8_dsl/mapping.py
elasticsearch8_dsl/query.py
elasticsearch8_dsl/search.py
elasticsearch8_dsl/serializer.py
elasticsearch8_dsl/update_by_query.py
elasticsearch8_dsl/utils.py
elasticsearch8_dsl/wrappers.py
elasticsearch8_dsl/response/__init__.py
elasticsearch8_dsl/response/aggs.py
elasticsearch8_dsl/response/hit.py
elasticsearch8_dsl-8.12.0.dist-info/AUTHORS
elasticsearch8_dsl-8.12.0.dist-info/LICENSE
elasticsearch8_dsl-8.12.0.dist-info/METADATA
elasticsearch8_dsl-8.12.0.dist-info/WHEEL
elasticsearch8_dsl-8.12.0.dist-info/top_level.txt
elasticsearch8_dsl-8.12.0.dist-info/RECORD
