Metadata-Version: 2.1
Name: elasticsearch8-dsl
Version: 8.12.0
Summary: Python client for Elasticsearch
Home-page: https://github.com/elasticsearch/elasticsearch-dsl-py
Author: Elastic Client Library Maintainers
Author-email: client-libs@elastic.co
License: Apache-2.0
Classifier: Development Status :: 4 - Beta
Classifier: License :: OSI Approved :: Apache Software License
Classifier: Intended Audience :: Developers
Classifier: Operating System :: OS Independent
Classifier: Programming Language :: Python
Classifier: Programming Language :: Python :: 3
Classifier: Programming Language :: Python :: 3 :: Only
Classifier: Programming Language :: Python :: 3.7
Classifier: Programming Language :: Python :: 3.8
Classifier: Programming Language :: Python :: 3.9
Classifier: Programming Language :: Python :: 3.10
Classifier: Programming Language :: Python :: 3.11
Classifier: Programming Language :: Python :: 3.12
Classifier: Programming Language :: Python :: Implementation :: CPython
Classifier: Programming Language :: Python :: Implementation :: PyPy
Requires-Python: >=3.7
License-File: LICENSE
License-File: AUTHORS
Requires-Dist: python-dateutil
Requires-Dist: elasticsearch8 <9.0.0,>=8.0.0
Provides-Extra: develop
Requires-Dist: pytest ; extra == 'develop'
Requires-Dist: pytest-cov ; extra == 'develop'
Requires-Dist: pytest-mock ; extra == 'develop'
Requires-Dist: pytz ; extra == 'develop'
Requires-Dist: coverage ; extra == 'develop'
Requires-Dist: sphinx >2 ; extra == 'develop'
Requires-Dist: sphinx-rtd-theme >0.5 ; extra == 'develop'
